ml_digits_recognition/__init__.py
ml_digits_recognition/drawing.py
ml_digits_recognition/html_drawing_flask.py
ml_digits_recognition/model_precise.pt
ml_digits_recognition/neural_network.py
ml_digits_recognition/passenger_wsgi.py
ml_digits_recognition/run_app.py
ml_digits_recognition-1.4.0.dist-info/licenses/LICENSE
tests/__init__.py
tests/test_digits.py
ml_digits_recognition-1.4.0.dist-info/METADATA
ml_digits_recognition-1.4.0.dist-info/WHEEL
ml_digits_recognition-1.4.0.dist-info/top_level.txt
ml_digits_recognition-1.4.0.dist-info/RECORD
