Metadata-Version: 2.4
Name: ml_digits_recognition
Version: 1.4.0
Summary: A simple digits recognition neural network
Author: Martin
Project-URL: Homepage, https://github.com/MartinBraquet/ml-digits-recognition
Project-URL: Bug Tracker, https://github.com/MartinBraquet/ml-digits-recognition/issues
Classifier: Programming Language :: Python :: 3
Classifier: License :: OSI Approved :: MIT License
Classifier: Operating System :: OS Independent
Requires-Python: >=3.7
License-File: LICENSE
Requires-Dist: torch
Requires-Dist: torchvision
Requires-Dist: Pillow
Provides-Extra: dev
Requires-Dist: pytest; extra == "dev"
Requires-Dist: pytest-cov; extra == "dev"
Requires-Dist: pytest-env; extra == "dev"
Requires-Dist: pip-tools; extra == "dev"
Requires-Dist: build; extra == "dev"
Dynamic: license-file
